litepipeline_helper/__init__.py
litepipeline_helper/version.py
litepipeline_helper/models/__init__.py
litepipeline_helper/models/action.py
litepipeline_helper/models/client.py
litepipeline_helper-0.1.2.dist-info/METADATA
litepipeline_helper-0.1.2.dist-info/WHEEL
litepipeline_helper-0.1.2.dist-info/top_level.txt
litepipeline_helper-0.1.2.dist-info/RECORD
