Metadata-Version: 2.1
Name: litepipeline-helper
Version: 0.1.2
Summary: LitePipeline helper: help user to develop LitePipeline's application
Home-page: https://github.com/fiefdx/LitePipeline
Author: fiefdx
Author-email: fiefdx@163.com
License: MIT
Classifier: License :: OSI Approved :: MIT License
Classifier: Programming Language :: Python :: 3
Classifier: Programming Language :: Python :: 3.7
Requires-Dist: requests >=2.22.0
Requires-Dist: tea-encrypt
